{
  "league_id": 3,
  "week": 12,
  "homeTeam": "Stan's Sturgeons",
  "homeScore": "20",
  "homeRoster": [
    "Amos Lee",
    "Jamie Wildgen",
    "Mackenzie King",
    "Rob Tyson",
    "Karen Kavanagh",
    "Kathryn Jarrett-Ekholm",
    "Frederic Caron",
    "James Maeng",
    "Patrick Kenzie",
    "Stanley Kent",
    "Ashlin Kelly(S)"
  ],
  "awayTeam": "Luke Parity",
  "awayScore": "20",
  "awayRoster": [
    "Alex Bush",
    "Andre Scott",
    "Greg Probe",
    "Marc Vachon",
    "Hope Celani",
    "Jessie Robinson",
    "Jeff Hunt",
    "Kyle Sprysa",
    "Nick Klimowicz",
    "Steve Chow",
    "Heather Wallace",
    "Ewelina Sosnowska"
  ],
  "points": [
    {
      "offensePlayers": [
        "Alex Bush",
        "Andre Scott",
        "Greg Probe",
        "Marc Vachon",
        "Hope Celani",
        "Jessie Robinson"
      ],
      "defensePlayers": [
        "Amos Lee",
        "Jamie Wildgen",
        "Mackenzie King",
        "Rob Tyson",
        "Karen Kavanagh",
        "Kathryn Jarrett-Ekholm"
      ],
      "events": [
        {
          "type": "PULL",
          "firstActor": "Amos Lee"
        },
        {
          "type": "PASS",
          "firstActor": "Greg Probe",
          "secondActor": "Alex Bush"
        },
        {
          "type": "PASS",
          "firstActor": "Alex Bush",
          "secondActor": "Jessie Robinson"
        },
        {
          "type": "PASS",
          "firstActor": "Jessie Robinson",
          "secondActor": "Greg Probe"
        },
        {
          "type": "PASS",
          "firstActor": "Greg Probe",
          "secondActor": "Hope Celani"
        },
        {
          "type": "PASS",
          "firstActor": "Hope Celani",
          "secondActor": "Greg Probe"
        },
        {
          "type": "PASS",
          "firstActor": "Greg Probe",
          "secondActor": "Jessie Robinson"
        },
        {
          "type": "PASS",
          "firstActor": "Jessie Robinson",
          "secondActor": "Alex Bush"
        },
        {
          "type": "POINT",
          "firstActor": "Alex Bush"
        }
      ]
    },
    {
      "offensePlayers": [
        "Frederic Caron",
        "James Maeng",
        "Patrick Kenzie",
        "Stanley Kent",
        "Kathryn Jarrett-Ekholm",
        "Ashlin Kelly(S)"
      ],
      "defensePlayers": [
        "Jeff Hunt",
        "Kyle Sprysa",
        "Nick Klimowicz",
        "Steve Chow",
        "Heather Wallace",
        "Jessie Robinson"
      ],
      "events": [
        {
          "type": "PASS",
          "firstActor": "Stanley Kent",
          "secondActor": "James Maeng"
        },
        {
          "type": "PASS",
          "firstActor": "James Maeng",
          "secondActor": "Ashlin Kelly(S)"
        },
        {
          "type": "PASS",
          "firstActor": "Ashlin Kelly(S)",
          "secondActor": "Stanley Kent"
        },
        {
          "type": "PASS",
          "firstActor": "Stanley Kent",
          "secondActor": "Ashlin Kelly(S)"
        },
        {
          "type": "POINT",
          "firstActor": "Ashlin Kelly(S)"
        }
      ]
    },
    {
      "offensePlayers": [
        "Alex Bush",
        "Andre Scott",
        "Greg Probe",
        "Marc Vachon",
        "Heather Wallace",
        "Hope Celani"
      ],
      "defensePlayers": [
        "Amos Lee",
        "Jamie Wildgen",
        "Mackenzie King",
        "Rob Tyson",
        "Karen Kavanagh",
        "Ashlin Kelly(S)"
      ],
      "events": [
        {
          "type": "PASS",
          "firstActor": "Greg Probe",
          "secondActor": "Alex Bush"
        },
        {
          "type": "PASS",
          "firstActor": "Alex Bush",
          "secondActor": "Greg Probe"
        },
        {
          "type": "PASS",
          "firstActor": "Greg Probe",
          "secondActor": "Heather Wallace"
        },
        {
          "type": "PASS",
          "firstActor": "Heather Wallace",
          "secondActor": "Greg Probe"
        },
        {
          "type": "PASS",
          "firstActor": "Greg Probe",
          "secondActor": "Hope Celani"
        },
        {
          "type": "DROP",
          "firstActor": "Hope Celani"
        },
        {
          "type": "PASS",
          "firstActor": "Rob Tyson",
          "secondActor": "Karen Kavanagh"
        },
        {
          "type": "PASS",
          "firstActor": "Karen Kavanagh",
          "secondActor": "Amos Lee"
        },
        {
          "type": "THROWAWAY",
          "firstActor": "Amos Lee"
        },
        {
          "type": "PASS",
          "firstActor": "Greg Probe",
          "secondActor": "Alex Bush"
        },
        {
          "type": "THROWAWAY",
          "firstActor": "Alex Bush"
        },
        {
          "type": "PASS",
          "firstActor": "Karen Kavanagh",
          "secondActor": "Mackenzie King"
        },
        {
          "type": "PASS",
          "firstActor": "Mackenzie King",
          "secondActor": "Jamie Wildgen"
        },
        {
          "type": "PASS",
          "firstActor": "Jamie Wildgen",
          "secondActor": "Ashlin Kelly(S)"
        },
        {
          "type": "PASS",
          "firstActor": "Ashlin Kelly(S)",
          "secondActor": "Amos Lee"
        },
        {
          "type": "THROWAWAY",
          "firstActor": "Amos Lee"
        },
        {
          "type": "PASS",
          "firstActor": "Heather Wallace",
          "secondActor": "Greg Probe"
        },
        {
          "type": "PASS",
          "firstActor": "Greg Probe",
          "secondActor": "Heather Wallace"
        },
        {
          "type": "PASS",
          "firstActor": "Heather Wallace",
          "secondActor": "Greg Probe"
        },
        {
          "type": "DROP",
          "firstActor": "Greg Probe"
        },
        {
          "type": "PASS",
          "firstActor": "Amos Lee",
          "secondActor": "Ashlin Kelly(S)"
        },
        {
          "type": "POINT",
          "firstActor": "Ashlin Kelly(S)"
        }
      ]
    },
    {
      "offensePlayers": [
        "Jeff Hunt",
        "Kyle Sprysa",
        "Nick Klimowicz",
        "Steve Chow",
        "Hope Celani",
        "Jessie Robinson"
      ],
      "defensePlayers": [
        "Frederic Caron",
        "James Maeng",
        "Patrick Kenzie",
        "Stanley Kent",
        "Karen Kavanagh",
        "Kathryn Jarrett-Ekholm"
      ],
      "events": [
        {
          "type": "PASS",
          "firstActor": "Nick Klimowicz",
          "secondActor": "Kyle Sprysa"
        },
        {
          "type": "THROWAWAY",
          "firstActor": "Kyle Sprysa"
        },
        {
          "type": "DEFENSE",
          "firstActor": "James Maeng"
        },
        {
          "type": "PASS",
          "firstActor": "James Maeng",
          "secondActor": "Karen Kavanagh"
        },
        {
          "type": "PASS",
          "firstActor": "Karen Kavanagh",
          "secondActor": "Stanley Kent"
        },
        {
          "type": "PASS",
          "firstActor": "Stanley Kent",
          "secondActor": "Kathryn Jarrett-Ekholm"
        },
        {
          "type": "PASS",
          "firstActor": "Kathryn Jarrett-Ekholm",
          "secondActor": "Karen Kavanagh"
        },
        {
          "type": "PASS",
          "firstActor": "Karen Kavanagh",
          "secondActor": "James Maeng"
        },
        {
          "type": "POINT",
          "firstActor": "James Maeng"
        }
      ]
    },
    {
      "offensePlayers": [
        "Alex Bush",
        "Andre Scott",
        "Greg Probe",
        "Marc Vachon",
        "Heather Wallace",
        "Jessie Robinson"
      ],
      "defensePlayers": [
        "Amos Lee",
        "Jamie Wildgen",
        "Mackenzie King",
        "Rob Tyson",
        "Kathryn Jarrett-Ekholm",
        "Ashlin Kelly(S)"
      ],
      "events": [
        {
          "type": "PASS",
          "firstActor": "Jessie Robinson",
          "secondActor": "Alex Bush"
        },
        {
          "type": "PASS",
          "firstActor": "Alex Bush",
          "secondActor": "Andre Scott"
        },
        {
          "type": "POINT",
          "firstActor": "Andre Scott"
        }
      ]
    },
    {
      "offensePlayers": [
        "Frederic Caron",
        "James Maeng",
        "Patrick Kenzie",
        "Stanley Kent",
        "Karen Kavanagh",
        "Ashlin Kelly(S)"
      ],
      "defensePlayers": [
        "Jeff Hunt",
        "Kyle Sprysa",
        "Nick Klimowicz",
        "Steve Chow",
        "Heather Wallace",
        "Hope Celani"
      ],
      "events": [
        {
          "type": "PASS",
          "firstActor": "Stanley Kent",
          "secondActor": "Karen Kavanagh"
        },
        {
          "type": "PASS",
          "firstActor": "Karen Kavanagh",
          "secondActor": "Frederic Caron"
        },
        {
          "type": "THROWAWAY",
          "firstActor": "Frederic Caron"
        },
        {
          "type": "PASS",
          "firstActor": "Nick Klimowicz",
          "secondActor": "Jeff Hunt"
        },
        {
          "type": "PASS",
          "firstActor": "Jeff Hunt",
          "secondActor": "Heather Wallace"
        },
        {
          "type": "PASS",
          "firstActor": "Heather Wallace",
          "secondActor": "Kyle Sprysa"
        },
        {
          "type": "THROWAWAY",
          "firstActor": "Kyle Sprysa"
        },
        {
          "type": "PASS",
          "firstActor": "Stanley Kent",
          "secondActor": "Frederic Caron"
        },
        {
          "type": "POINT",
          "firstActor": "Frederic Caron"
        }
      ]
    },
    {
      "offensePlayers": [
        "Alex Bush",
        "Andre Scott",
        "Greg Probe",
        "Marc Vachon",
        "Hope Celani",
        "Jessie Robinson"
      ],
      "defensePlayers": [
        "Amos Lee",
        "Jamie Wildgen",
        "Mackenzie King",
        "Rob Tyson",
        "Karen Kavanagh",
        "Kathryn Jarrett-Ekholm"
      ],
      "events": [
        {
          "type": "PASS",
          "firstActor": "Greg Probe",
          "secondActor": "Jessie Robinson"
        },
        {
          "type": "PASS",
          "firstActor": "Jessie Robinson",
          "secondActor": "Greg Probe"
        },
        {
          "type": "PASS",
          "firstActor": "Greg Probe",
          "secondActor": "Hope Celani"
        },
        {
          "type": "PASS",
          "firstActor": "Hope Celani",
          "secondActor": "Alex Bush"
        },
        {
          "type": "PASS",
          "firstActor": "Alex Bush",
          "secondActor": "Hope Celani"
        },
        {
          "type": "PASS",
          "firstActor": "Hope Celani",
          "secondActor": "Jessie Robinson"
        },
        {
          "type": "POINT",
          "firstActor": "Jessie Robinson"
        }
      ]
    },
    {
      "offensePlayers": [
        "Frederic Caron",
        "James Maeng",
        "Patrick Kenzie",
        "Stanley Kent",
        "Kathryn Jarrett-Ekholm",
        "Ashlin Kelly(S)"
      ],
      "defensePlayers": [
        "Jeff Hunt",
        "Kyle Sprysa",
        "Nick Klimowicz",
        "Steve Chow",
        "Heather Wallace",
        "Hope Celani"
      ],
      "events": [
        {
          "type": "PASS",
          "firstActor": "Stanley Kent",
          "secondActor": "Frederic Caron"
        },
        {
          "type": "DROP",
          "firstActor": "Frederic Caron"
        },
        {
          "type": "PASS",
          "firstActor": "Jeff Hunt",
          "secondActor": "Kyle Sprysa"
        },
        {
          "type": "PASS",
          "firstActor": "Kyle Sprysa",
          "secondActor": "Jeff Hunt"
        },
        {
          "type": "PASS",
          "firstActor": "Jeff Hunt",
          "secondActor": "Steve Chow"
        },
        {
          "type": "PASS",
          "firstActor": "Steve Chow",
          "secondActor": "Hope Celani"
        },
        {
          "type": "PASS",
          "firstActor": "Hope Celani",
          "secondActor": "Steve Chow"
        },
        {
          "type": "PASS",
          "firstActor": "Steve Chow",
          "secondActor": "Nick Klimowicz"
        },
        {
          "type": "PASS",
          "firstActor": "Nick Klimowicz",
          "secondActor": "Jeff Hunt"
        },
        {
          "type": "THROWAWAY",
          "firstActor": "Jeff Hunt"
        },
        {
          "type": "DEFENSE",
          "firstActor": "Frederic Caron"
        },
        {
          "type": "PASS",
          "firstActor": "Frederic Caron",
          "secondActor": "Stanley Kent"
        },
        {
          "type": "PASS",
          "firstActor": "Stanley Kent",
          "secondActor": "Ashlin Kelly(S)"
        },
        {
          "type": "POINT",
          "firstActor": "Ashlin Kelly(S)"
        }
      ]
    },
    {
      "offensePlayers": [
        "Alex Bush",
        "Andre Scott",
        "Greg Probe",
        "Marc Vachon",
        "Jessie Robinson",
        "Ewelina Sosnowska"
      ],
      "defensePlayers": [
        "Amos Lee",
        "Jamie Wildgen",
        "Mackenzie King",
        "Rob Tyson",
        "Karen Kavanagh",
        "Ashlin Kelly(S)"
      ],
      "events": [
        {
          "type": "PASS",
          "firstActor": "Jessie Robinson",
          "secondActor": "Alex Bush"
        },
        {
          "type": "PASS",
          "firstActor": "Alex Bush",
          "secondActor": "Marc Vachon"
        },
        {
          "type": "PASS",
          "firstActor": "Marc Vachon",
          "secondActor": "Ewelina Sosnowska"
        },
        {
          "type": "PASS",
          "firstActor": "Ewelina Sosnowska",
          "secondActor": "Marc Vachon"
        },
        {
          "type": "PASS",
          "firstActor": "Marc Vachon",
          "secondActor": "Greg Probe"
        },
        {
          "type": "PASS",
          "firstActor": "Greg Probe",
          "secondActor": "Jessie Robinson"
        },
        {
          "type": "PASS",
          "firstActor": "Jessie Robinson",
          "secondActor": "Greg Probe"
        },
        {
          "type": "PASS",
          "firstActor": "Greg Probe",
          "secondActor": "Alex Bush"
        },
        {
          "type": "PASS",
          "firstActor": "Alex Bush",
          "secondActor": "Greg Probe"
        },
        {
          "type": "PASS",
          "firstActor": "Greg Probe",
          "secondActor": "Alex Bush"
        },
        {
          "type": "THROWAWAY",
          "firstActor": "Alex Bush"
        },
        {
          "type": "DEFENSE",
          "firstActor": "Amos Lee"
        },
        {
          "type": "PASS",
          "firstActor": "Amos Lee",
          "secondActor": "Jamie Wildgen"
        },
        {
          "type": "PASS",
          "firstActor": "Jamie Wildgen",
          "secondActor": "Ashlin Kelly(S)"
        },
        {
          "type": "PASS",
          "firstActor": "Ashlin Kelly(S)",
          "secondActor": "Jamie Wildgen"
        },
        {
          "type": "PASS",
          "firstActor": "Jamie Wildgen",
          "secondActor": "Amos Lee"
        },
        {
          "type": "PASS",
          "firstActor": "Amos Lee",
          "secondActor": "Ashlin Kelly(S)"
        },
        {
          "type": "POINT",
          "firstActor": "Ashlin Kelly(S)"
        }
      ]
    },
    {
      "offensePlayers": [
        "Jeff Hunt",
        "Kyle Sprysa",
        "Nick Klimowicz",
        "Steve Chow",
        "Heather Wallace",
        "Hope Celani"
      ],
      "defensePlayers": [
        "Frederic Caron",
        "James Maeng",
        "Patrick Kenzie",
        "Stanley Kent",
        "Karen Kavanagh",
        "Kathryn Jarrett-Ekholm"
      ],
      "events": [
        {
          "type": "PASS",
          "firstActor": "Steve Chow",
          "secondActor": "Heather Wallace"
        },
        {
          "type": "PASS",
          "firstActor": "Heather Wallace",
          "secondActor": "Nick Klimowicz"
        },
        {
          "type": "PASS",
          "firstActor": "Nick Klimowicz",
          "secondActor": "Steve Chow"
        },
        {
          "type": "POINT",
          "firstActor": "Steve Chow"
        }
      ]
    },
    {
      "offensePlayers": [
        "Amos Lee",
        "Jamie Wildgen",
        "Mackenzie King",
        "Rob Tyson",
        "Kathryn Jarrett-Ekholm",
        "Ashlin Kelly(S)"
      ],
      "defensePlayers": [
        "Alex Bush",
        "Andre Scott",
        "Greg Probe",
        "Marc Vachon",
        "Jessie Robinson",
        "Ewelina Sosnowska"
      ],
      "events": [
        {
          "type": "PASS",
          "firstActor": "Mackenzie King",
          "secondActor": "Amos Lee"
        },
        {
          "type": "PASS",
          "firstActor": "Amos Lee",
          "secondActor": "Jamie Wildgen"
        },
        {
          "type": "PASS",
          "firstActor": "Jamie Wildgen",
          "secondActor": "Amos Lee"
        },
        {
          "type": "PASS",
          "firstActor": "Amos Lee",
          "secondActor": "Jamie Wildgen"
        },
        {
          "type": "PASS",
          "firstActor": "Jamie Wildgen",
          "secondActor": "Ashlin Kelly(S)"
        },
        {
          "type": "POINT",
          "firstActor": "Ashlin Kelly(S)"
        }
      ]
    },
    {
      "offensePlayers": [
        "Jeff Hunt",
        "Kyle Sprysa",
        "Nick Klimowicz",
        "Steve Chow",
        "Heather Wallace",
        "Hope Celani"
      ],
      "defensePlayers": [
        "Frederic Caron",
        "James Maeng",
        "Patrick Kenzie",
        "Stanley Kent",
        "Karen Kavanagh",
        "Ashlin Kelly(S)"
      ],
      "events": [
        {
          "type": "PASS",
          "firstActor": "Steve Chow",
          "secondActor": "Nick Klimowicz"
        },
        {
          "type": "PASS",
          "firstActor": "Nick Klimowicz",
          "secondActor": "Steve Chow"
        },
        {
          "type": "PASS",
          "firstActor": "Steve Chow",
          "secondActor": "Heather Wallace"
        },
        {
          "type": "PASS",
          "firstActor": "Heather Wallace",
          "secondActor": "Jeff Hunt"
        },
        {
          "type": "PASS",
          "firstActor": "Jeff Hunt",
          "secondActor": "Kyle Sprysa"
        },
        {
          "type": "PASS",
          "firstActor": "Kyle Sprysa",
          "secondActor": "Jeff Hunt"
        },
        {
          "type": "PASS",
          "firstActor": "Jeff Hunt",
          "secondActor": "Hope Celani"
        },
        {
          "type": "PASS",
          "firstActor": "Hope Celani",
          "secondActor": "Steve Chow"
        },
        {
          "type": "PASS",
          "firstActor": "Steve Chow",
          "secondActor": "Heather Wallace"
        },
        {
          "type": "THROWAWAY",
          "firstActor": "Heather Wallace"
        },
        {
          "type": "DEFENSE",
          "firstActor": "Patrick Kenzie"
        },
        {
          "type": "PASS",
          "firstActor": "Patrick Kenzie",
          "secondActor": "James Maeng"
        },
        {
          "type": "PASS",
          "firstActor": "James Maeng",
          "secondActor": "Ashlin Kelly(S)"
        },
        {
          "type": "DROP",
          "firstActor": "Ashlin Kelly(S)"
        },
        {
          "type": "PASS",
          "firstActor": "Heather Wallace",
          "secondActor": "Kyle Sprysa"
        },
        {
          "type": "PASS",
          "firstActor": "Kyle Sprysa",
          "secondActor": "Hope Celani"
        },
        {
          "type": "DROP",
          "firstActor": "Hope Celani"
        },
        {
          "type": "PASS",
          "firstActor": "Karen Kavanagh",
          "secondActor": "Ashlin Kelly(S)"
        },
        {
          "type": "THROWAWAY",
          "firstActor": "Ashlin Kelly(S)"
        },
        {
          "type": "DEFENSE",
          "firstActor": "Kyle Sprysa"
        },
        {
          "type": "PASS",
          "firstActor": "Kyle Sprysa",
          "secondActor": "Steve Chow"
        },
        {
          "type": "PASS",
          "firstActor": "Steve Chow",
          "secondActor": "Kyle Sprysa"
        },
        {
          "type": "PASS",
          "firstActor": "Kyle Sprysa",
          "secondActor": "Nick Klimowicz"
        },
        {
          "type": "PASS",
          "firstActor": "Nick Klimowicz",
          "secondActor": "Hope Celani"
        },
        {
          "type": "PASS",
          "firstActor": "Hope Celani",
          "secondActor": "Kyle Sprysa"
        },
        {
          "type": "POINT",
          "firstActor": "Kyle Sprysa"
        }
      ]
    },
    {
      "offensePlayers": [
        "Amos Lee",
        "Jamie Wildgen",
        "Mackenzie King",
        "Rob Tyson",
        "Karen Kavanagh",
        "Kathryn Jarrett-Ekholm"
      ],
      "defensePlayers": [
        "Alex Bush",
        "Andre Scott",
        "Greg Probe",
        "Marc Vachon",
        "Jessie Robinson",
        "Ewelina Sosnowska"
      ],
      "events": [
        {
          "type": "PASS",
          "firstActor": "Rob Tyson",
          "secondActor": "Jamie Wildgen"
        },
        {
          "type": "PASS",
          "firstActor": "Jamie Wildgen",
          "secondActor": "Amos Lee"
        },
        {
          "type": "PASS",
          "firstActor": "Amos Lee",
          "secondActor": "Jamie Wildgen"
        },
        {
          "type": "POINT",
          "firstActor": "Jamie Wildgen"
        }
      ]
    },
    {
      "offensePlayers": [
        "Jeff Hunt",
        "Kyle Sprysa",
        "Nick Klimowicz",
        "Steve Chow",
        "Heather Wallace",
        "Hope Celani"
      ],
      "defensePlayers": [
        "Frederic Caron",
        "James Maeng",
        "Patrick Kenzie",
        "Stanley Kent",
        "Kathryn Jarrett-Ekholm",
        "Ashlin Kelly(S)"
      ],
      "events": [
        {
          "type": "PASS",
          "firstActor": "Steve Chow",
          "secondActor": "Nick Klimowicz"
        },
        {
          "type": "PASS",
          "firstActor": "Nick Klimowicz",
          "secondActor": "Heather Wallace"
        },
        {
          "type": "PASS",
          "firstActor": "Heather Wallace",
          "secondActor": "Kyle Sprysa"
        },
        {
          "type": "PASS",
          "firstActor": "Kyle Sprysa",
          "secondActor": "Steve Chow"
        },
        {
          "type": "PASS",
          "firstActor": "Steve Chow",
          "secondActor": "Heather Wallace"
        },
        {
          "type": "DROP",
          "firstActor": "Heather Wallace"
        },
        {
          "type": "PASS",
          "firstActor": "Patrick Kenzie",
          "secondActor": "James Maeng"
        },
        {
          "type": "PASS",
          "firstActor": "James Maeng",
          "secondActor": "Stanley Kent"
        },
        {
          "type": "PASS",
          "firstActor": "Stanley Kent",
          "secondActor": "Patrick Kenzie"
        },
        {
          "type": "PASS",
          "firstActor": "Patrick Kenzie",
          "secondActor": "Ashlin Kelly(S)"
        },
        {
          "type": "PASS",
          "firstActor": "Ashlin Kelly(S)",
          "secondActor": "Frederic Caron"
        },
        {
          "type": "PASS",
          "firstActor": "Frederic Caron",
          "secondActor": "Stanley Kent"
        },
        {
          "type": "DROP",
          "firstActor": "Stanley Kent"
        },
        {
          "type": "THROWAWAY",
          "firstActor": "Nick Klimowicz"
        },
        {
          "type": "PASS",
          "firstActor": "Frederic Caron",
          "secondActor": "Patrick Kenzie"
        },
        {
          "type": "PASS",
          "firstActor": "Patrick Kenzie",
          "secondActor": "Stanley Kent"
        },
        {
          "type": "DROP",
          "firstActor": "Stanley Kent"
        },
        {
          "type": "PASS",
          "firstActor": "Nick Klimowicz",
          "secondActor": "Kyle Sprysa"
        },
        {
          "type": "PASS",
          "firstActor": "Kyle Sprysa",
          "secondActor": "Jeff Hunt"
        },
        {
          "type": "PASS",
          "firstActor": "Jeff Hunt",
          "secondActor": "Heather Wallace"
        },
        {
          "type": "PASS",
          "firstActor": "Heather Wallace",
          "secondActor": "Hope Celani"
        },
        {
          "type": "PASS",
          "firstActor": "Hope Celani",
          "secondActor": "Steve Chow"
        },
        {
          "type": "POINT",
          "firstActor": "Steve Chow"
        }
      ]
    },
    {
      "offensePlayers": [
        "Amos Lee",
        "Jamie Wildgen",
        "Mackenzie King",
        "Rob Tyson",
        "Karen Kavanagh",
        "Ashlin Kelly(S)"
      ],
      "defensePlayers": [
        "Alex Bush",
        "Andre Scott",
        "Greg Probe",
        "Marc Vachon",
        "Jessie Robinson",
        "Ewelina Sosnowska"
      ],
      "events": [
        {
          "type": "PASS",
          "firstActor": "Mackenzie King",
          "secondActor": "Jamie Wildgen"
        },
        {
          "type": "DROP",
          "firstActor": "Jamie Wildgen"
        },
        {
          "type": "PASS",
          "firstActor": "Alex Bush",
          "secondActor": "Jessie Robinson"
        },
        {
          "type": "PASS",
          "firstActor": "Jessie Robinson",
          "secondActor": "Greg Probe"
        },
        {
          "type": "PASS",
          "firstActor": "Greg Probe",
          "secondActor": "Alex Bush"
        },
        {
          "type": "POINT",
          "firstActor": "Alex Bush"
        }
      ]
    },
    {
      "offensePlayers": [
        "Frederic Caron",
        "James Maeng",
        "Patrick Kenzie",
        "Stanley Kent",
        "Karen Kavanagh",
        "Kathryn Jarrett-Ekholm"
      ],
      "defensePlayers": [
        "Jeff Hunt",
        "Kyle Sprysa",
        "Nick Klimowicz",
        "Steve Chow",
        "Heather Wallace",
        "Hope Celani"
      ],
      "events": [
        {
          "type": "PASS",
          "firstActor": "Stanley Kent",
          "secondActor": "Frederic Caron"
        },
        {
          "type": "PASS",
          "firstActor": "Frederic Caron",
          "secondActor": "Kathryn Jarrett-Ekholm"
        },
        {
          "type": "POINT",
          "firstActor": "Kathryn Jarrett-Ekholm"
        }
      ]
    },
    {
      "offensePlayers": [
        "Alex Bush",
        "Andre Scott",
        "Greg Probe",
        "Marc Vachon",
        "Jessie Robinson",
        "Ewelina Sosnowska"
      ],
      "defensePlayers": [
        "Amos Lee",
        "Jamie Wildgen",
        "Mackenzie King",
        "Rob Tyson",
        "Kathryn Jarrett-Ekholm",
        "Ashlin Kelly(S)"
      ],
      "events": [
        {
          "type": "PASS",
          "firstActor": "Greg Probe",
          "secondActor": "Jessie Robinson"
        },
        {
          "type": "THROWAWAY",
          "firstActor": "Jessie Robinson"
        },
        {
          "type": "PASS",
          "firstActor": "Amos Lee",
          "secondActor": "Jamie Wildgen"
        },
        {
          "type": "PASS",
          "firstActor": "Jamie Wildgen",
          "secondActor": "Ashlin Kelly(S)"
        },
        {
          "type": "PASS",
          "firstActor": "Ashlin Kelly(S)",
          "secondActor": "Kathryn Jarrett-Ekholm"
        },
        {
          "type": "PASS",
          "firstActor": "Kathryn Jarrett-Ekholm",
          "secondActor": "Jamie Wildgen"
        },
        {
          "type": "POINT",
          "firstActor": "Jamie Wildgen"
        }
      ]
    },
    {
      "offensePlayers": [
        "Jeff Hunt",
        "Kyle Sprysa",
        "Nick Klimowicz",
        "Steve Chow",
        "Heather Wallace",
        "Hope Celani"
      ],
      "defensePlayers": [
        "Frederic Caron",
        "James Maeng",
        "Patrick Kenzie",
        "Stanley Kent",
        "Karen Kavanagh",
        "Ashlin Kelly(S)"
      ],
      "events": [
        {
          "type": "PASS",
          "firstActor": "Nick Klimowicz",
          "secondActor": "Hope Celani"
        },
        {
          "type": "PASS",
          "firstActor": "Hope Celani",
          "secondActor": "Jeff Hunt"
        },
        {
          "type": "PASS",
          "firstActor": "Jeff Hunt",
          "secondActor": "Nick Klimowicz"
        },
        {
          "type": "PASS",
          "firstActor": "Nick Klimowicz",
          "secondActor": "Heather Wallace"
        },
        {
          "type": "POINT",
          "firstActor": "Heather Wallace"
        }
      ]
    },
    {
      "offensePlayers": [
        "Amos Lee",
        "Jamie Wildgen",
        "Mackenzie King",
        "Rob Tyson",
        "Karen Kavanagh",
        "Kathryn Jarrett-Ekholm"
      ],
      "defensePlayers": [
        "Alex Bush",
        "Andre Scott",
        "Greg Probe",
        "Marc Vachon",
        "Jessie Robinson",
        "Ewelina Sosnowska"
      ],
      "events": [
        {
          "type": "PASS",
          "firstActor": "Mackenzie King",
          "secondActor": "Karen Kavanagh"
        },
        {
          "type": "PASS",
          "firstActor": "Karen Kavanagh",
          "secondActor": "Amos Lee"
        },
        {
          "type": "PASS",
          "firstActor": "Amos Lee",
          "secondActor": "Jamie Wildgen"
        },
        {
          "type": "PASS",
          "firstActor": "Jamie Wildgen",
          "secondActor": "Amos Lee"
        },
        {
          "type": "PASS",
          "firstActor": "Amos Lee",
          "secondActor": "Mackenzie King"
        },
        {
          "type": "PASS",
          "firstActor": "Mackenzie King",
          "secondActor": "Jamie Wildgen"
        },
        {
          "type": "PASS",
          "firstActor": "Jamie Wildgen",
          "secondActor": "Rob Tyson"
        },
        {
          "type": "PASS",
          "firstActor": "Rob Tyson",
          "secondActor": "Kathryn Jarrett-Ekholm"
        },
        {
          "type": "PASS",
          "firstActor": "Kathryn Jarrett-Ekholm",
          "secondActor": "Amos Lee"
        },
        {
          "type": "THROWAWAY",
          "firstActor": "Amos Lee"
        },
        {
          "type": "DEFENSE",
          "firstActor": "Alex Bush"
        },
        {
          "type": "PASS",
          "firstActor": "Jessie Robinson",
          "secondActor": "Alex Bush"
        },
        {
          "type": "PASS",
          "firstActor": "Alex Bush",
          "secondActor": "Ewelina Sosnowska"
        },
        {
          "type": "PASS",
          "firstActor": "Ewelina Sosnowska",
          "secondActor": "Marc Vachon"
        },
        {
          "type": "PASS",
          "firstActor": "Marc Vachon",
          "secondActor": "Greg Probe"
        },
        {
          "type": "PASS",
          "firstActor": "Greg Probe",
          "secondActor": "Alex Bush"
        },
        {
          "type": "PASS",
          "firstActor": "Alex Bush",
          "secondActor": "Jessie Robinson"
        },
        {
          "type": "POINT",
          "firstActor": "Jessie Robinson"
        }
      ]
    },
    {
      "offensePlayers": [
        "Frederic Caron",
        "James Maeng",
        "Patrick Kenzie",
        "Stanley Kent",
        "Kathryn Jarrett-Ekholm",
        "Ashlin Kelly(S)"
      ],
      "defensePlayers": [
        "Jeff Hunt",
        "Kyle Sprysa",
        "Nick Klimowicz",
        "Steve Chow",
        "Heather Wallace",
        "Hope Celani"
      ],
      "events": [
        {
          "type": "PASS",
          "firstActor": "Stanley Kent",
          "secondActor": "Patrick Kenzie"
        },
        {
          "type": "THROWAWAY",
          "firstActor": "Patrick Kenzie"
        },
        {
          "type": "PASS",
          "firstActor": "Steve Chow",
          "secondActor": "Heather Wallace"
        },
        {
          "type": "PASS",
          "firstActor": "Heather Wallace",
          "secondActor": "Kyle Sprysa"
        },
        {
          "type": "PASS",
          "firstActor": "Kyle Sprysa",
          "secondActor": "Nick Klimowicz"
        },
        {
          "type": "DROP",
          "firstActor": "Nick Klimowicz"
        },
        {
          "type": "PASS",
          "firstActor": "Frederic Caron",
          "secondActor": "Stanley Kent"
        },
        {
          "type": "POINT",
          "firstActor": "Stanley Kent"
        }
      ]
    },
    {
      "offensePlayers": [
        "Alex Bush",
        "Andre Scott",
        "Greg Probe",
        "Marc Vachon",
        "Jessie Robinson",
        "Ewelina Sosnowska"
      ],
      "defensePlayers": [
        "Amos Lee",
        "Jamie Wildgen",
        "Mackenzie King",
        "Rob Tyson",
        "Karen Kavanagh",
        "Ashlin Kelly(S)"
      ],
      "events": [
        {
          "type": "PASS",
          "firstActor": "Greg Probe",
          "secondActor": "Marc Vachon"
        },
        {
          "type": "PASS",
          "firstActor": "Marc Vachon",
          "secondActor": "Jessie Robinson"
        },
        {
          "type": "PASS",
          "firstActor": "Jessie Robinson",
          "secondActor": "Greg Probe"
        },
        {
          "type": "PASS",
          "firstActor": "Greg Probe",
          "secondActor": "Ewelina Sosnowska"
        },
        {
          "type": "POINT",
          "firstActor": "Ewelina Sosnowska"
        }
      ]
    },
    {
      "offensePlayers": [
        "Frederic Caron",
        "James Maeng",
        "Patrick Kenzie",
        "Stanley Kent",
        "Karen Kavanagh",
        "Kathryn Jarrett-Ekholm"
      ],
      "defensePlayers": [
        "Jeff Hunt",
        "Kyle Sprysa",
        "Nick Klimowicz",
        "Steve Chow",
        "Heather Wallace",
        "Hope Celani"
      ],
      "events": [
        {
          "type": "PULL",
          "firstActor": "Nick Klimowicz"
        },
        {
          "type": "PASS",
          "firstActor": "Stanley Kent",
          "secondActor": "Patrick Kenzie"
        },
        {
          "type": "PASS",
          "firstActor": "Patrick Kenzie",
          "secondActor": "Frederic Caron"
        },
        {
          "type": "PASS",
          "firstActor": "Frederic Caron",
          "secondActor": "Stanley Kent"
        },
        {
          "type": "PASS",
          "firstActor": "Stanley Kent",
          "secondActor": "Frederic Caron"
        },
        {
          "type": "PASS",
          "firstActor": "Frederic Caron",
          "secondActor": "Stanley Kent"
        },
        {
          "type": "PASS",
          "firstActor": "Stanley Kent",
          "secondActor": "Frederic Caron"
        },
        {
          "type": "PASS",
          "firstActor": "Frederic Caron",
          "secondActor": "James Maeng"
        },
        {
          "type": "PASS",
          "firstActor": "James Maeng",
          "secondActor": "Frederic Caron"
        },
        {
          "type": "PASS",
          "firstActor": "Frederic Caron",
          "secondActor": "Kathryn Jarrett-Ekholm"
        },
        {
          "type": "POINT",
          "firstActor": "Kathryn Jarrett-Ekholm"
        }
      ]
    },
    {
      "offensePlayers": [
        "Alex Bush",
        "Andre Scott",
        "Greg Probe",
        "Marc Vachon",
        "Jessie Robinson",
        "Ewelina Sosnowska"
      ],
      "defensePlayers": [
        "Amos Lee",
        "Jamie Wildgen",
        "Mackenzie King",
        "Rob Tyson",
        "Kathryn Jarrett-Ekholm",
        "Ashlin Kelly(S)"
      ],
      "events": [
        {
          "type": "PASS",
          "firstActor": "Greg Probe",
          "secondActor": "Jessie Robinson"
        },
        {
          "type": "PASS",
          "firstActor": "Jessie Robinson",
          "secondActor": "Alex Bush"
        },
        {
          "type": "POINT",
          "firstActor": "Alex Bush"
        }
      ]
    },
    {
      "offensePlayers": [
        "Frederic Caron",
        "James Maeng",
        "Patrick Kenzie",
        "Stanley Kent",
        "Karen Kavanagh",
        "Ashlin Kelly(S)"
      ],
      "defensePlayers": [
        "Jeff Hunt",
        "Kyle Sprysa",
        "Nick Klimowicz",
        "Steve Chow",
        "Heather Wallace",
        "Hope Celani"
      ],
      "events": [
        {
          "type": "PASS",
          "firstActor": "Stanley Kent",
          "secondActor": "Ashlin Kelly(S)"
        },
        {
          "type": "PASS",
          "firstActor": "Ashlin Kelly(S)",
          "secondActor": "Patrick Kenzie"
        },
        {
          "type": "PASS",
          "firstActor": "Patrick Kenzie",
          "secondActor": "Ashlin Kelly(S)"
        },
        {
          "type": "PASS",
          "firstActor": "Ashlin Kelly(S)",
          "secondActor": "Frederic Caron"
        },
        {
          "type": "PASS",
          "firstActor": "Frederic Caron",
          "secondActor": "Stanley Kent"
        },
        {
          "type": "POINT",
          "firstActor": "Stanley Kent"
        }
      ]
    },
    {
      "offensePlayers": [
        "Alex Bush",
        "Andre Scott",
        "Greg Probe",
        "Marc Vachon",
        "Jessie Robinson",
        "Ewelina Sosnowska"
      ],
      "defensePlayers": [
        "Amos Lee",
        "Jamie Wildgen",
        "Mackenzie King",
        "Rob Tyson",
        "Karen Kavanagh",
        "Kathryn Jarrett-Ekholm"
      ],
      "events": [
        {
          "type": "PASS",
          "firstActor": "Greg Probe",
          "secondActor": "Alex Bush"
        },
        {
          "type": "PASS",
          "firstActor": "Alex Bush",
          "secondActor": "Marc Vachon"
        },
        {
          "type": "PASS",
          "firstActor": "Marc Vachon",
          "secondActor": "Greg Probe"
        },
        {
          "type": "PASS",
          "firstActor": "Greg Probe",
          "secondActor": "Marc Vachon"
        },
        {
          "type": "PASS",
          "firstActor": "Marc Vachon",
          "secondActor": "Greg Probe"
        },
        {
          "type": "PASS",
          "firstActor": "Greg Probe",
          "secondActor": "Ewelina Sosnowska"
        },
        {
          "type": "PASS",
          "firstActor": "Ewelina Sosnowska",
          "secondActor": "Alex Bush"
        },
        {
          "type": "PASS",
          "firstActor": "Alex Bush",
          "secondActor": "Marc Vachon"
        },
        {
          "type": "PASS",
          "firstActor": "Marc Vachon",
          "secondActor": "Andre Scott"
        },
        {
          "type": "PASS",
          "firstActor": "Andre Scott",
          "secondActor": "Jessie Robinson"
        },
        {
          "type": "THROWAWAY",
          "firstActor": "Jessie Robinson"
        },
        {
          "type": "PASS",
          "firstActor": "Rob Tyson",
          "secondActor": "Jamie Wildgen"
        },
        {
          "type": "PASS",
          "firstActor": "Jamie Wildgen",
          "secondActor": "Amos Lee"
        },
        {
          "type": "PASS",
          "firstActor": "Amos Lee",
          "secondActor": "Karen Kavanagh"
        },
        {
          "type": "PASS",
          "firstActor": "Karen Kavanagh",
          "secondActor": "Jamie Wildgen"
        },
        {
          "type": "POINT",
          "firstActor": "Jamie Wildgen"
        }
      ]
    },
    {
      "offensePlayers": [
        "Jeff Hunt",
        "Kyle Sprysa",
        "Nick Klimowicz",
        "Steve Chow",
        "Heather Wallace",
        "Hope Celani"
      ],
      "defensePlayers": [
        "Frederic Caron",
        "James Maeng",
        "Patrick Kenzie",
        "Stanley Kent",
        "Kathryn Jarrett-Ekholm",
        "Ashlin Kelly(S)"
      ],
      "events": [
        {
          "type": "THROWAWAY",
          "firstActor": "Nick Klimowicz"
        },
        {
          "type": "DEFENSE",
          "firstActor": "Frederic Caron"
        },
        {
          "type": "PASS",
          "firstActor": "Frederic Caron",
          "secondActor": "Stanley Kent"
        },
        {
          "type": "POINT",
          "firstActor": "Stanley Kent"
        }
      ]
    },
    {
      "offensePlayers": [
        "Alex Bush",
        "Andre Scott",
        "Greg Probe",
        "Marc Vachon",
        "Jessie Robinson",
        "Ewelina Sosnowska"
      ],
      "defensePlayers": [
        "Amos Lee",
        "Jamie Wildgen",
        "Mackenzie King",
        "Rob Tyson",
        "Karen Kavanagh",
        "Ashlin Kelly(S)"
      ],
      "events": [
        {
          "type": "PASS",
          "firstActor": "Greg Probe",
          "secondActor": "Alex Bush"
        },
        {
          "type": "PASS",
          "firstActor": "Alex Bush",
          "secondActor": "Jessie Robinson"
        },
        {
          "type": "PASS",
          "firstActor": "Jessie Robinson",
          "secondActor": "Marc Vachon"
        },
        {
          "type": "PASS",
          "firstActor": "Marc Vachon",
          "secondActor": "Greg Probe"
        },
        {
          "type": "PASS",
          "firstActor": "Greg Probe",
          "secondActor": "Andre Scott"
        },
        {
          "type": "PASS",
          "firstActor": "Andre Scott",
          "secondActor": "Alex Bush"
        },
        {
          "type": "PASS",
          "firstActor": "Alex Bush",
          "secondActor": "Marc Vachon"
        },
        {
          "type": "POINT",
          "firstActor": "Marc Vachon"
        }
      ]
    },
    {
      "offensePlayers": [
        "Frederic Caron",
        "James Maeng",
        "Patrick Kenzie",
        "Stanley Kent",
        "Karen Kavanagh",
        "Kathryn Jarrett-Ekholm"
      ],
      "defensePlayers": [
        "Jeff Hunt",
        "Kyle Sprysa",
        "Nick Klimowicz",
        "Steve Chow",
        "Heather Wallace",
        "Hope Celani"
      ],
      "events": [
        {
          "type": "PASS",
          "firstActor": "Patrick Kenzie",
          "secondActor": "James Maeng"
        },
        {
          "type": "PASS",
          "firstActor": "James Maeng",
          "secondActor": "Frederic Caron"
        },
        {
          "type": "PASS",
          "firstActor": "Frederic Caron",
          "secondActor": "Stanley Kent"
        },
        {
          "type": "PASS",
          "firstActor": "Stanley Kent",
          "secondActor": "Frederic Caron"
        },
        {
          "type": "THROWAWAY",
          "firstActor": "Frederic Caron"
        },
        {
          "type": "PASS",
          "firstActor": "Kyle Sprysa",
          "secondActor": "Nick Klimowicz"
        },
        {
          "type": "PASS",
          "firstActor": "Nick Klimowicz",
          "secondActor": "Kyle Sprysa"
        },
        {
          "type": "PASS",
          "firstActor": "Kyle Sprysa",
          "secondActor": "Hope Celani"
        },
        {
          "type": "PASS",
          "firstActor": "Hope Celani",
          "secondActor": "Heather Wallace"
        },
        {
          "type": "THROWAWAY",
          "firstActor": "Heather Wallace"
        },
        {
          "type": "PASS",
          "firstActor": "Frederic Caron",
          "secondActor": "Kathryn Jarrett-Ekholm"
        },
        {
          "type": "PASS",
          "firstActor": "Kathryn Jarrett-Ekholm",
          "secondActor": "James Maeng"
        },
        {
          "type": "POINT",
          "firstActor": "James Maeng"
        }
      ]
    },
    {
      "offensePlayers": [
        "Alex Bush",
        "Andre Scott",
        "Greg Probe",
        "Marc Vachon",
        "Jessie Robinson",
        "Ewelina Sosnowska"
      ],
      "defensePlayers": [
        "Amos Lee",
        "Jamie Wildgen",
        "Mackenzie King",
        "Rob Tyson",
        "Kathryn Jarrett-Ekholm",
        "Ashlin Kelly(S)"
      ],
      "events": [
        {
          "type": "THROWAWAY",
          "firstActor": "Greg Probe"
        },
        {
          "type": "DEFENSE",
          "firstActor": "Kathryn Jarrett-Ekholm"
        },
        {
          "type": "PASS",
          "firstActor": "Rob Tyson",
          "secondActor": "Mackenzie King"
        },
        {
          "type": "PASS",
          "firstActor": "Mackenzie King",
          "secondActor": "Kathryn Jarrett-Ekholm"
        },
        {
          "type": "DROP",
          "firstActor": "Kathryn Jarrett-Ekholm"
        },
        {
          "type": "PASS",
          "firstActor": "Jessie Robinson",
          "secondActor": "Greg Probe"
        },
        {
          "type": "PASS",
          "firstActor": "Greg Probe",
          "secondActor": "Jessie Robinson"
        },
        {
          "type": "PASS",
          "firstActor": "Jessie Robinson",
          "secondActor": "Marc Vachon"
        },
        {
          "type": "PASS",
          "firstActor": "Marc Vachon",
          "secondActor": "Greg Probe"
        },
        {
          "type": "PASS",
          "firstActor": "Greg Probe",
          "secondActor": "Ewelina Sosnowska"
        },
        {
          "type": "THROWAWAY",
          "firstActor": "Ewelina Sosnowska"
        },
        {
          "type": "DEFENSE",
          "firstActor": "Amos Lee"
        },
        {
          "type": "PASS",
          "firstActor": "Amos Lee",
          "secondActor": "Mackenzie King"
        },
        {
          "type": "POINT",
          "firstActor": "Mackenzie King"
        }
      ]
    },
    {
      "offensePlayers": [
        "Jeff Hunt",
        "Kyle Sprysa",
        "Nick Klimowicz",
        "Steve Chow",
        "Heather Wallace",
        "Hope Celani"
      ],
      "defensePlayers": [
        "Frederic Caron",
        "James Maeng",
        "Patrick Kenzie",
        "Stanley Kent",
        "Karen Kavanagh",
        "Ashlin Kelly(S)"
      ],
      "events": [
        {
          "type": "PASS",
          "firstActor": "Steve Chow",
          "secondActor": "Kyle Sprysa"
        },
        {
          "type": "PASS",
          "firstActor": "Kyle Sprysa",
          "secondActor": "Heather Wallace"
        },
        {
          "type": "PASS",
          "firstActor": "Heather Wallace",
          "secondActor": "Steve Chow"
        },
        {
          "type": "PASS",
          "firstActor": "Steve Chow",
          "secondActor": "Heather Wallace"
        },
        {
          "type": "PASS",
          "firstActor": "Heather Wallace",
          "secondActor": "Kyle Sprysa"
        },
        {
          "type": "PASS",
          "firstActor": "Kyle Sprysa",
          "secondActor": "Hope Celani"
        },
        {
          "type": "PASS",
          "firstActor": "Hope Celani",
          "secondActor": "Steve Chow"
        },
        {
          "type": "PASS",
          "firstActor": "Steve Chow",
          "secondActor": "Nick Klimowicz"
        },
        {
          "type": "PASS",
          "firstActor": "Nick Klimowicz",
          "secondActor": "Hope Celani"
        },
        {
          "type": "POINT",
          "firstActor": "Hope Celani"
        }
      ]
    },
    {
      "offensePlayers": [
        "Amos Lee",
        "Jamie Wildgen",
        "Mackenzie King",
        "Rob Tyson",
        "Karen Kavanagh",
        "Kathryn Jarrett-Ekholm"
      ],
      "defensePlayers": [
        "Alex Bush",
        "Andre Scott",
        "Greg Probe",
        "Marc Vachon",
        "Jessie Robinson",
        "Ewelina Sosnowska"
      ],
      "events": [
        {
          "type": "THROWAWAY",
          "firstActor": "Mackenzie King"
        },
        {
          "type": "PASS",
          "firstActor": "Alex Bush",
          "secondActor": "Andre Scott"
        },
        {
          "type": "POINT",
          "firstActor": "Andre Scott"
        }
      ]
    },
    {
      "offensePlayers": [
        "Frederic Caron",
        "James Maeng",
        "Patrick Kenzie",
        "Stanley Kent",
        "Kathryn Jarrett-Ekholm",
        "Ashlin Kelly(S)"
      ],
      "defensePlayers": [
        "Jeff Hunt",
        "Kyle Sprysa",
        "Nick Klimowicz",
        "Steve Chow",
        "Heather Wallace",
        "Hope Celani"
      ],
      "events": [
        {
          "type": "PASS",
          "firstActor": "Stanley Kent",
          "secondActor": "Patrick Kenzie"
        },
        {
          "type": "PASS",
          "firstActor": "Patrick Kenzie",
          "secondActor": "James Maeng"
        },
        {
          "type": "PASS",
          "firstActor": "James Maeng",
          "secondActor": "Stanley Kent"
        },
        {
          "type": "PASS",
          "firstActor": "Stanley Kent",
          "secondActor": "Patrick Kenzie"
        },
        {
          "type": "PASS",
          "firstActor": "Patrick Kenzie",
          "secondActor": "James Maeng"
        },
        {
          "type": "DROP",
          "firstActor": "James Maeng"
        },
        {
          "type": "PASS",
          "firstActor": "Nick Klimowicz",
          "secondActor": "Jeff Hunt"
        },
        {
          "type": "PASS",
          "firstActor": "Jeff Hunt",
          "secondActor": "Nick Klimowicz"
        },
        {
          "type": "PASS",
          "firstActor": "Nick Klimowicz",
          "secondActor": "Heather Wallace"
        },
        {
          "type": "PASS",
          "firstActor": "Heather Wallace",
          "secondActor": "Nick Klimowicz"
        },
        {
          "type": "THROWAWAY",
          "firstActor": "Nick Klimowicz"
        },
        {
          "type": "DEFENSE",
          "firstActor": "Patrick Kenzie"
        },
        {
          "type": "THROWAWAY",
          "firstActor": "Frederic Caron"
        },
        {
          "type": "DEFENSE",
          "firstActor": "Nick Klimowicz"
        },
        {
          "type": "PASS",
          "firstActor": "Nick Klimowicz",
          "secondActor": "Hope Celani"
        },
        {
          "type": "PASS",
          "firstActor": "Hope Celani",
          "secondActor": "Steve Chow"
        },
        {
          "type": "DROP",
          "firstActor": "Steve Chow"
        },
        {
          "type": "PASS",
          "firstActor": "Frederic Caron",
          "secondActor": "Patrick Kenzie"
        },
        {
          "type": "PASS",
          "firstActor": "Patrick Kenzie",
          "secondActor": "James Maeng"
        },
        {
          "type": "DROP",
          "firstActor": "James Maeng"
        },
        {
          "type": "PASS",
          "firstActor": "Kyle Sprysa",
          "secondActor": "Nick Klimowicz"
        },
        {
          "type": "POINT",
          "firstActor": "Nick Klimowicz"
        }
      ]
    },
    {
      "offensePlayers": [
        "Amos Lee",
        "Jamie Wildgen",
        "Mackenzie King",
        "Rob Tyson",
        "Karen Kavanagh",
        "Ashlin Kelly(S)"
      ],
      "defensePlayers": [
        "Alex Bush",
        "Andre Scott",
        "Greg Probe",
        "Marc Vachon",
        "Jessie Robinson",
        "Ewelina Sosnowska"
      ],
      "events": [
        {
          "type": "PASS",
          "firstActor": "Rob Tyson",
          "secondActor": "Jamie Wildgen"
        },
        {
          "type": "PASS",
          "firstActor": "Jamie Wildgen",
          "secondActor": "Amos Lee"
        },
        {
          "type": "PASS",
          "firstActor": "Amos Lee",
          "secondActor": "Ashlin Kelly(S)"
        },
        {
          "type": "POINT",
          "firstActor": "Ashlin Kelly(S)"
        }
      ]
    },
    {
      "offensePlayers": [
        "Jeff Hunt",
        "Kyle Sprysa",
        "Nick Klimowicz",
        "Steve Chow",
        "Heather Wallace",
        "Hope Celani"
      ],
      "defensePlayers": [
        "Frederic Caron",
        "James Maeng",
        "Patrick Kenzie",
        "Stanley Kent",
        "Karen Kavanagh",
        "Kathryn Jarrett-Ekholm"
      ],
      "events": [
        {
          "type": "PASS",
          "firstActor": "Steve Chow",
          "secondActor": "Hope Celani"
        },
        {
          "type": "PASS",
          "firstActor": "Hope Celani",
          "secondActor": "Heather Wallace"
        },
        {
          "type": "PASS",
          "firstActor": "Heather Wallace",
          "secondActor": "Kyle Sprysa"
        },
        {
          "type": "PASS",
          "firstActor": "Kyle Sprysa",
          "secondActor": "Jeff Hunt"
        },
        {
          "type": "POINT",
          "firstActor": "Jeff Hunt"
        }
      ]
    },
    {
      "offensePlayers": [
        "Amos Lee",
        "Jamie Wildgen",
        "Mackenzie King",
        "Rob Tyson",
        "Kathryn Jarrett-Ekholm",
        "Ashlin Kelly(S)"
      ],
      "defensePlayers": [
        "Alex Bush",
        "Andre Scott",
        "Greg Probe",
        "Marc Vachon",
        "Jessie Robinson",
        "Ewelina Sosnowska"
      ],
      "events": [
        {
          "type": "PASS",
          "firstActor": "Mackenzie King",
          "secondActor": "Jamie Wildgen"
        },
        {
          "type": "PASS",
          "firstActor": "Jamie Wildgen",
          "secondActor": "Amos Lee"
        },
        {
          "type": "PASS",
          "firstActor": "Amos Lee",
          "secondActor": "Jamie Wildgen"
        },
        {
          "type": "PASS",
          "firstActor": "Jamie Wildgen",
          "secondActor": "Mackenzie King"
        },
        {
          "type": "PASS",
          "firstActor": "Mackenzie King",
          "secondActor": "Ashlin Kelly(S)"
        },
        {
          "type": "POINT",
          "firstActor": "Ashlin Kelly(S)"
        }
      ]
    },
    {
      "offensePlayers": [
        "Jeff Hunt",
        "Kyle Sprysa",
        "Nick Klimowicz",
        "Steve Chow",
        "Heather Wallace",
        "Hope Celani"
      ],
      "defensePlayers": [
        "Frederic Caron",
        "James Maeng",
        "Patrick Kenzie",
        "Stanley Kent",
        "Karen Kavanagh",
        "Ashlin Kelly(S)"
      ],
      "events": [
        {
          "type": "PASS",
          "firstActor": "Nick Klimowicz",
          "secondActor": "Steve Chow"
        },
        {
          "type": "THROWAWAY",
          "firstActor": "Steve Chow"
        },
        {
          "type": "PASS",
          "firstActor": "Patrick Kenzie",
          "secondActor": "James Maeng"
        },
        {
          "type": "PASS",
          "firstActor": "James Maeng",
          "secondActor": "Karen Kavanagh"
        },
        {
          "type": "DROP",
          "firstActor": "Karen Kavanagh"
        },
        {
          "type": "PASS",
          "firstActor": "Heather Wallace",
          "secondActor": "Kyle Sprysa"
        },
        {
          "type": "THROWAWAY",
          "firstActor": "Kyle Sprysa"
        },
        {
          "type": "PASS",
          "firstActor": "Stanley Kent",
          "secondActor": "James Maeng"
        },
        {
          "type": "PASS",
          "firstActor": "James Maeng",
          "secondActor": "Patrick Kenzie"
        },
        {
          "type": "PASS",
          "firstActor": "Patrick Kenzie",
          "secondActor": "Ashlin Kelly(S)"
        },
        {
          "type": "THROWAWAY",
          "firstActor": "Ashlin Kelly(S)"
        },
        {
          "type": "DEFENSE",
          "firstActor": "Kyle Sprysa"
        },
        {
          "type": "PASS",
          "firstActor": "Kyle Sprysa",
          "secondActor": "Hope Celani"
        },
        {
          "type": "PASS",
          "firstActor": "Hope Celani",
          "secondActor": "Heather Wallace"
        },
        {
          "type": "THROWAWAY",
          "firstActor": "Heather Wallace"
        },
        {
          "type": "PASS",
          "firstActor": "Patrick Kenzie",
          "secondActor": "Frederic Caron"
        },
        {
          "type": "THROWAWAY",
          "firstActor": "Frederic Caron"
        },
        {
          "type": "PASS",
          "firstActor": "Kyle Sprysa",
          "secondActor": "Nick Klimowicz"
        },
        {
          "type": "PASS",
          "firstActor": "Nick Klimowicz",
          "secondActor": "Steve Chow"
        },
        {
          "type": "PASS",
          "firstActor": "Steve Chow",
          "secondActor": "Jeff Hunt"
        },
        {
          "type": "POINT",
          "firstActor": "Jeff Hunt"
        }
      ]
    },
    {
      "offensePlayers": [
        "Amos Lee",
        "Jamie Wildgen",
        "Mackenzie King",
        "Rob Tyson",
        "Karen Kavanagh",
        "Kathryn Jarrett-Ekholm"
      ],
      "defensePlayers": [
        "Alex Bush",
        "Andre Scott",
        "Greg Probe",
        "Marc Vachon",
        "Jessie Robinson",
        "Ewelina Sosnowska"
      ],
      "events": [
        {
          "type": "PASS",
          "firstActor": "Rob Tyson",
          "secondActor": "Amos Lee"
        },
        {
          "type": "PASS",
          "firstActor": "Amos Lee",
          "secondActor": "Mackenzie King"
        },
        {
          "type": "PASS",
          "firstActor": "Mackenzie King",
          "secondActor": "Jamie Wildgen"
        },
        {
          "type": "PASS",
          "firstActor": "Jamie Wildgen",
          "secondActor": "Karen Kavanagh"
        },
        {
          "type": "PASS",
          "firstActor": "Karen Kavanagh",
          "secondActor": "Mackenzie King"
        },
        {
          "type": "PASS",
          "firstActor": "Mackenzie King",
          "secondActor": "Kathryn Jarrett-Ekholm"
        },
        {
          "type": "PASS",
          "firstActor": "Kathryn Jarrett-Ekholm",
          "secondActor": "Mackenzie King"
        },
        {
          "type": "POINT",
          "firstActor": "Mackenzie King"
        }
      ]
    },
    {
      "offensePlayers": [
        "Jeff Hunt",
        "Kyle Sprysa",
        "Nick Klimowicz",
        "Steve Chow",
        "Heather Wallace",
        "Hope Celani"
      ],
      "defensePlayers": [
        "Frederic Caron",
        "James Maeng",
        "Patrick Kenzie",
        "Stanley Kent",
        "Kathryn Jarrett-Ekholm",
        "Ashlin Kelly(S)"
      ],
      "events": [
        {
          "type": "PASS",
          "firstActor": "Nick Klimowicz",
          "secondActor": "Steve Chow"
        },
        {
          "type": "PASS",
          "firstActor": "Steve Chow",
          "secondActor": "Nick Klimowicz"
        },
        {
          "type": "PASS",
          "firstActor": "Nick Klimowicz",
          "secondActor": "Steve Chow"
        },
        {
          "type": "PASS",
          "firstActor": "Steve Chow",
          "secondActor": "Jeff Hunt"
        },
        {
          "type": "PASS",
          "firstActor": "Jeff Hunt",
          "secondActor": "Kyle Sprysa"
        },
        {
          "type": "POINT",
          "firstActor": "Kyle Sprysa"
        }
      ]
    },
    {
      "offensePlayers": [
        "Amos Lee",
        "Jamie Wildgen",
        "Mackenzie King",
        "Rob Tyson",
        "Karen Kavanagh",
        "Ashlin Kelly(S)"
      ],
      "defensePlayers": [
        "Alex Bush",
        "Andre Scott",
        "Greg Probe",
        "Marc Vachon",
        "Jessie Robinson",
        "Ewelina Sosnowska"
      ],
      "events": [
        {
          "type": "PASS",
          "firstActor": "Mackenzie King",
          "secondActor": "Jamie Wildgen"
        },
        {
          "type": "PASS",
          "firstActor": "Jamie Wildgen",
          "secondActor": "Rob Tyson"
        },
        {
          "type": "THROWAWAY",
          "firstActor": "Rob Tyson"
        },
        {
          "type": "DEFENSE",
          "firstActor": "Alex Bush"
        },
        {
          "type": "PASS",
          "firstActor": "Jessie Robinson",
          "secondActor": "Marc Vachon"
        },
        {
          "type": "PASS",
          "firstActor": "Marc Vachon",
          "secondActor": "Alex Bush"
        },
        {
          "type": "PASS",
          "firstActor": "Alex Bush",
          "secondActor": "Greg Probe"
        },
        {
          "type": "PASS",
          "firstActor": "Greg Probe",
          "secondActor": "Marc Vachon"
        },
        {
          "type": "PASS",
          "firstActor": "Marc Vachon",
          "secondActor": "Jessie Robinson"
        },
        {
          "type": "PASS",
          "firstActor": "Jessie Robinson",
          "secondActor": "Marc Vachon"
        },
        {
          "type": "PASS",
          "firstActor": "Marc Vachon",
          "secondActor": "Alex Bush"
        },
        {
          "type": "PASS",
          "firstActor": "Alex Bush",
          "secondActor": "Jessie Robinson"
        },
        {
          "type": "PASS",
          "firstActor": "Jessie Robinson",
          "secondActor": "Marc Vachon"
        },
        {
          "type": "POINT",
          "firstActor": "Marc Vachon"
        }
      ]
    },
    {
      "offensePlayers": [
        "Frederic Caron",
        "James Maeng",
        "Patrick Kenzie",
        "Stanley Kent",
        "Karen Kavanagh",
        "Kathryn Jarrett-Ekholm"
      ],
      "defensePlayers": [
        "Jeff Hunt",
        "Kyle Sprysa",
        "Nick Klimowicz",
        "Steve Chow",
        "Heather Wallace",
        "Hope Celani"
      ],
      "events": [
        {
          "type": "PASS",
          "firstActor": "Stanley Kent",
          "secondActor": "Frederic Caron"
        },
        {
          "type": "PASS",
          "firstActor": "Frederic Caron",
          "secondActor": "Karen Kavanagh"
        },
        {
          "type": "PASS",
          "firstActor": "Karen Kavanagh",
          "secondActor": "Patrick Kenzie"
        },
        {
          "type": "PASS",
          "firstActor": "Patrick Kenzie",
          "secondActor": "Karen Kavanagh"
        },
        {
          "type": "PASS",
          "firstActor": "Karen Kavanagh",
          "secondActor": "Patrick Kenzie"
        },
        {
          "type": "PASS",
          "firstActor": "Patrick Kenzie",
          "secondActor": "Stanley Kent"
        },
        {
          "type": "PASS",
          "firstActor": "Stanley Kent",
          "secondActor": "Karen Kavanagh"
        },
        {
          "type": "PASS",
          "firstActor": "Karen Kavanagh",
          "secondActor": "Frederic Caron"
        },
        {
          "type": "PASS",
          "firstActor": "Frederic Caron",
          "secondActor": "Stanley Kent"
        },
        {
          "type": "PASS",
          "firstActor": "Stanley Kent",
          "secondActor": "Frederic Caron"
        },
        {
          "type": "PASS",
          "firstActor": "Frederic Caron",
          "secondActor": "Stanley Kent"
        },
        {
          "type": "DROP",
          "firstActor": "Stanley Kent"
        },
        {
          "type": "PASS",
          "firstActor": "Heather Wallace",
          "secondActor": "Nick Klimowicz"
        },
        {
          "type": "PASS",
          "firstActor": "Nick Klimowicz",
          "secondActor": "Heather Wallace"
        },
        {
          "type": "PASS",
          "firstActor": "Heather Wallace",
          "secondActor": "Jeff Hunt"
        },
        {
          "type": "PASS",
          "firstActor": "Jeff Hunt",
          "secondActor": "Steve Chow"
        },
        {
          "type": "PASS",
          "firstActor": "Steve Chow",
          "secondActor": "Kyle Sprysa"
        },
        {
          "type": "PASS",
          "firstActor": "Kyle Sprysa",
          "secondActor": "Hope Celani"
        },
        {
          "type": "POINT",
          "firstActor": "Hope Celani"
        }
      ]
    }
  ]
}
